apread/__init__.py
apread/apreader.py
apread/binaryReader.py
apread/entries.py
apread/loader.py
apread/tools.py
apread-1.1.2.dist-info/LICENSE.txt
apread-1.1.2.dist-info/METADATA
apread-1.1.2.dist-info/WHEEL
apread-1.1.2.dist-info/top_level.txt
apread-1.1.2.dist-info/RECORD
