Metadata-Version: 2.1
Name: apread
Version: 1.1.2
Summary: Import data from CatmanAP binary files.
Author-email: Leon Bohmann <mail@leonbohmann.de>
Project-URL: Homepage, https://github.com/leonbohmann/APReader
Project-URL: Bug Tracker, https://github.com/leonbohmann/APReader/issues
Classifier: Programming Language :: Python :: 3
Classifier: License :: OSI Approved :: MIT License
Classifier: Operating System :: OS Independent
Requires-Python: >=3.9
License-File: LICENSE.txt
Requires-Dist: matplotlib
Requires-Dist: opencv-python
Requires-Dist: numpy
Requires-Dist: tqdm
